pkg/BeewiPy.py
pkg/__init__.py
iot_beewipy-0.0.1.dist-info/LICENSE.txt
iot_beewipy-0.0.1.dist-info/METADATA
iot_beewipy-0.0.1.dist-info/WHEEL
iot_beewipy-0.0.1.dist-info/top_level.txt
iot_beewipy-0.0.1.dist-info/RECORD
