Metadata-Version: 2.1
Name: iot-beewipy
Version: 0.0.1
Summary: A python library to interact with Beewi SmartBulb
Home-page: https://github.com/Kawakon/BeewiPy
Author: Kawakon Quansah
Author-email: kquan078@uottawa.ca
License: UNKNOWN
Platform: UNKNOWN
Classifier: Programming Language :: Python :: 3
Classifier: License :: OSI Approved :: MIT License
Classifier: Operating System :: OS Independent
Requires-Python: >=3.6
License-File: LICENSE.txt
